ZhishiGongxiangXieyiShiyongChangjianWentijiedaFeiguanfangFanyiXiangmu/README.md
ZhishiGongxiangXieyiShiyongChangjianWentijiedaFeiguanfangFanyiXiangmu/__init__.py
ZhishiGongxiangXieyiShiyongChangjianWentijiedaFeiguanfangFanyiXiangmu/__main__.py
ZhishiGongxiangXieyiShiyongChangjianWentijiedaFeiguanfangFanyiXiangmu/file.epub
ZhishiGongxiangXieyiShiyongChangjianWentijiedaFeiguanfangFanyiXiangmu/index.html
ZhishiGongxiangXieyiShiyongChangjianWentijiedaFeiguanfangFanyiXiangmu/css/__init__.py
ZhishiGongxiangXieyiShiyongChangjianWentijiedaFeiguanfangFanyiXiangmu/css/annotations.css
ZhishiGongxiangXieyiShiyongChangjianWentijiedaFeiguanfangFanyiXiangmu/css/main.css
ZhishiGongxiangXieyiShiyongChangjianWentijiedaFeiguanfangFanyiXiangmu/css/normalize.css
ZhishiGongxiangXieyiShiyongChangjianWentijiedaFeiguanfangFanyiXiangmu/css/popup.css
ZhishiGongxiangXieyiShiyongChangjianWentijiedaFeiguanfangFanyiXiangmu/font/__init__.py
ZhishiGongxiangXieyiShiyongChangjianWentijiedaFeiguanfangFanyiXiangmu/font/fontello.eot
ZhishiGongxiangXieyiShiyongChangjianWentijiedaFeiguanfangFanyiXiangmu/font/fontello.svg
ZhishiGongxiangXieyiShiyongChangjianWentijiedaFeiguanfangFanyiXiangmu/font/fontello.ttf
ZhishiGongxiangXieyiShiyongChangjianWentijiedaFeiguanfangFanyiXiangmu/font/fontello.woff
ZhishiGongxiangXieyiShiyongChangjianWentijiedaFeiguanfangFanyiXiangmu/img/__init__.py
ZhishiGongxiangXieyiShiyongChangjianWentijiedaFeiguanfangFanyiXiangmu/img/annotator-glyph-sprite.png
ZhishiGongxiangXieyiShiyongChangjianWentijiedaFeiguanfangFanyiXiangmu/img/annotator-icon-sprite.png
ZhishiGongxiangXieyiShiyongChangjianWentijiedaFeiguanfangFanyiXiangmu/img/apple-touch-icon.png
ZhishiGongxiangXieyiShiyongChangjianWentijiedaFeiguanfangFanyiXiangmu/img/cancelfullscreen.png
ZhishiGongxiangXieyiShiyongChangjianWentijiedaFeiguanfangFanyiXiangmu/img/close.png
ZhishiGongxiangXieyiShiyongChangjianWentijiedaFeiguanfangFanyiXiangmu/img/fullscreen.png
zhishi_gongxiang_xieyi_shiyong_changjian_wentijieda_feiguanfang_fanyi_xiangmu-2024.3.3.0.dist-info/METADATA
zhishi_gongxiang_xieyi_shiyong_changjian_wentijieda_feiguanfang_fanyi_xiangmu-2024.3.3.0.dist-info/WHEEL
zhishi_gongxiang_xieyi_shiyong_changjian_wentijieda_feiguanfang_fanyi_xiangmu-2024.3.3.0.dist-info/entry_points.txt
zhishi_gongxiang_xieyi_shiyong_changjian_wentijieda_feiguanfang_fanyi_xiangmu-2024.3.3.0.dist-info/top_level.txt
zhishi_gongxiang_xieyi_shiyong_changjian_wentijieda_feiguanfang_fanyi_xiangmu-2024.3.3.0.dist-info/RECORD
